boar_circularqueue/__init__.py
boar_circularqueue/container.py
boar_circularqueue/data.py
boar_circularqueue/utility.py
boar_circularqueue-0.2.2.dist-info/METADATA
boar_circularqueue-0.2.2.dist-info/WHEEL
boar_circularqueue-0.2.2.dist-info/top_level.txt
boar_circularqueue-0.2.2.dist-info/RECORD
