Metadata-Version: 2.1
Name: boar_circularqueue
Version: 0.2.2
Summary: A circular queue supports simple demo
Home-page: https://github.com/dexterchan/circularqueue
Author: Dexter Chan
Author-email: dexterchan@example.com
License: UNKNOWN
Keywords: boar_circularqueue
Platform: UNKNOWN
Classifier: Development Status :: 2 - Pre-Alpha
Classifier: Intended Audience :: Developers
Classifier: Natural Language :: English
Classifier: Programming Language :: Python :: 3
Classifier: Programming Language :: Python :: 3.8
Classifier: Programming Language :: Python :: 3.9
Classifier: Programming Language :: Python :: 3.11
Requires-Python: >=3.8
